thanakan/__init__.py
thanakan/models/FI_CODE.xlsx
thanakan/models/__init__.py
thanakan/models/bankcode.py
thanakan/services/__init__.py
thanakan/services/base.py
thanakan/services/kbank.py
thanakan/services/model/__init__.py
thanakan/services/model/common.py
thanakan/services/model/kbank.py
thanakan/services/model/scb.py
thanakan/services/model/status.txt
thanakan/services/scb.py
thanakan/slip/__init__.py
thanakan/slip/qrcode.py
thanakan-1.2.1.dist-info/entry_points.txt
thanakan-1.2.1.dist-info/LICENSE
thanakan-1.2.1.dist-info/WHEEL
thanakan-1.2.1.dist-info/METADATA
thanakan-1.2.1.dist-info/RECORD
